{
  "rooms": [
    {
      "id": "6246b6964f7a930001a7636a",
      "ownerID": "6242c206d3dd2500016583cb",
      "owner": {
        "userID": "6242c206d3dd2500016583cb",
        "displayName": "Gobierno de Navarra"
      },
      "name": "ESPACIO GOBIERNO DE NAVARRA",
      "slug": "ESPACIO-GOBIERNO-DE-NAVARRA",
      "description": "",
      "orgOwner": {
        "id": "6242f0b97aeff10001025a0b",
        "name": "GobiernoNavarra",
        "subscription": {
          "subscriptionType": "",
          "subscriptionSource": "",
          "isActive": false
        }
      },
      "organizations": [
        "6242f0b97aeff10001025a0b"
      ],
      "timeLastJoined": "0001-01-01T00:00:00Z",
      "thumbnails": [],
      "activeParticipants": [
        {
          "id": "62849a10bf651d0001db1a01",
          "displayName": "El Vigilante del Metaverso",
          "profilePicURL": "https://dd2cgqlmnwvp5.cloudfront.net/avatar_generic_bodies/rpm_male_tshirt/thumbnail.png",
          "avatarData": {
            "avatarUserID": "",
            "avatarID": "",
            "avatarBody": "https://dd2cgqlmnwvp5.cloudfront.net/avatar_generic_bodies/rpm_male_tshirt/model.glb",
            "filename": "",
            "skinColorOverride": "f0cdb5",
            "shirtColorOverride": "",
            "readyPlayerMeThumbnails": {
              "upperBody": "",
              "lowerBody": ""
            },
            "readyPlayerMeUrl": "",
            "ReadyPlayerMeUrlLastUpdated": "0001-01-01T00:00:00Z",
            "readyPlayerMeUrlCrunched": "",
            "readyPlayerMeUrlCrunchedBrotli": "",
            "ReadyPlayerMeUrlCrunchedLastUpdated": "0001-01-01T00:00:00Z",
            "activeAvatarStyle": "REALISTIC"
          },
          "appearanceCustomization": {
            "profileColor": "green"
          },
          "clientPlatforms": [
            "WebGL"
          ],
          "permissions": [],
          "clientPlatform": "",
          "playerColor": "green"
        },
        {
          "id": "628663e1bf651d0001db5519",
          "displayName": "Daniel",
          "profilePicURL": "https://dd2cgqlmnwvp5.cloudfront.net/avatar_generic_bodies/rpm_female_hijab/thumbnail.png",
          "avatarData": {
            "avatarUserID": "",
            "avatarID": "",
            "avatarBody": "https://dd2cgqlmnwvp5.cloudfront.net/avatar_generic_bodies/rpm_female_hijab/model.glb",
            "filename": "",
            "skinColorOverride": "",
            "shirtColorOverride": "",
            "readyPlayerMeThumbnails": {
              "upperBody": "",
              "lowerBody": ""
            },
            "readyPlayerMeUrl": "",
            "ReadyPlayerMeUrlLastUpdated": "0001-01-01T00:00:00Z",
            "readyPlayerMeUrlCrunched": "",
            "readyPlayerMeUrlCrunchedBrotli": "",
            "ReadyPlayerMeUrlCrunchedLastUpdated": "0001-01-01T00:00:00Z",
            "activeAvatarStyle": "REALISTIC"
          },
          "appearanceCustomization": {
            "profileColor": "orange"
          },
          "clientPlatforms": [
            "WebGL"
          ],
          "permissions": [],
          "clientPlatform": "",
          "playerColor": "orange"
        }
      ],
      "polymerVersion": 15,
      "roomThumbnails": {
        "transientGetUrl": "https://sapi-room-thumbnails.s3.amazonaws.com/6246b6964f7a930001a7636a/transientStateThumbnail?X-Amz-Algorithm=AWS4-HMAC-SHA256&X-Amz-Credential=ASIAVFTG5JZHGIIZL7UX%2F20220519%2Fus-east-1%2Fs3%2Faws4_request&X-Amz-Date=20220519T153919Z&X-Amz-Expires=14400&X-Amz-Security-Token=IQoJb3JpZ2luX2VjEBcaCXVzLWVhc3QtMSJHMEUCIQDFmscNntmUCd%2F%2B6P%2BkXbIbbdZF%2F93sRzM%2Bh0UktEfPPwIgds6qF2w13DF0lUFa11Dd55JZJCyoS%2B2mUBdBwrY1EF0q9wQI8P%2F%2F%2F%2F%2F%2F%2F%2F%2F%2FARADGgwzNTU2MjQzNzM4MzgiDPqvgS0a%2BZGpTC44fSrLBKnkEz8MgaSxoR6XvzJ7EZyyuFJaSnmPFQT3kCsUrzj%2F%2Bz0mebUQVsXtkTu%2BTMW5uId90rm%2Fno2YIGATsTJdC5MnBZ1L%2BRRpLFr426peuygXGWEB4d8DHX0v9lZx2i9X23tp5%2BWMlSoxzWpjG4aY9MMoCiP5m%2BmXWzrTAxiGWpB7t7EyTUWtmktcBqilOlohT5Jy2DP2pxu9HJIE5JAzywOzdtKMpkuEvM1NmzS5qcUpUDWivoxZNajT0gz%2Fa1Dnr0dr2Ngku1YkYBfpCdBnmh09lKQmb4pWmJoIw9fv%2BjRmAwhFcf6OW5xoKwWiYu3r7tzY0UEsqAI%2BpPaVnp9bU4j0B%2BsZKPergPVqEPwSQ0k1oPgzmAH%2FMRHg6FjcBYci74ojPIWWnDrU5s%2FD222jb9hPeHyUBGvGhfgWGD84do7E8XY54WAeeadhGCzfvuGTwhxbefLRY33GSQttMb%2FZu9Oj3uxHM9FSwSqZBHaW90lLxC43jgHkA9mdkB9Rex%2B%2B16VXN2HJz2jRPXo1RKlU%2FgvonLZJP%2FacBj%2FmBmmi7ncUDsTcqy5lmtcLsCMIk4E8K355SBLNv0%2FnLCrGw7R3OQ6MB4KdNYfQ1019aYNcpSoJcNWP%2BG8eXDqlEg%2BknTSptOmC7bz6mrFDKkuPzoHrsjAUBtTzkQoObv3beYyCalPgzyz0cHa28nXBrzjvacsOLS6sAvkqWyU1xB%2B7%2BPrfuynfLMgdlMlg1ZmI4x70b%2BM6IxbZqm%2B9scHpiOXnS97%2Fm0hdEh4hURYgvTnbMNuvmZQGOpoBiaVOPRkpQ0AsJAc%2B1PGg7bZwfQKdFrZ6gxwOkbH57TroM6NHeXUSOeHeAFUfslUIzxgxuT78l8vAGtNmItS%2FgyMPyy21EiIO%2FleKBrKFPMtT70LiAUXEB2qO56nqTiVzXHKTzI0KlKU7PadSrG0dXDfW1ISSzTsc2eDVO1EOKP3Wa%2BVsXE6LCjfyh6Tc%2BxrgVvOuByhfdvJCgg%3D%3D&X-Amz-SignedHeaders=host&X-Amz-Signature=3ed1c7a5e1f574ea3ca84d4bc5ebb941d05899eca485253aab02e340cc52cd58",
        "persistentGetUrl": "https://sapi-room-thumbnails.s3.amazonaws.com/6246b6964f7a930001a7636a/persistentStateThumbnail?X-Amz-Algorithm=AWS4-HMAC-SHA256&X-Amz-Credential=ASIAVFTG5JZHGIIZL7UX%2F20220519%2Fus-east-1%2Fs3%2Faws4_request&X-Amz-Date=20220519T153919Z&X-Amz-Expires=14400&X-Amz-Security-Token=IQoJb3JpZ2luX2VjEBcaCXVzLWVhc3QtMSJHMEUCIQDFmscNntmUCd%2F%2B6P%2BkXbIbbdZF%2F93sRzM%2Bh0UktEfPPwIgds6qF2w13DF0lUFa11Dd55JZJCyoS%2B2mUBdBwrY1EF0q9wQI8P%2F%2F%2F%2F%2F%2F%2F%2F%2F%2FARADGgwzNTU2MjQzNzM4MzgiDPqvgS0a%2BZGpTC44fSrLBKnkEz8MgaSxoR6XvzJ7EZyyuFJaSnmPFQT3kCsUrzj%2F%2Bz0mebUQVsXtkTu%2BTMW5uId90rm%2Fno2YIGATsTJdC5MnBZ1L%2BRRpLFr426peuygXGWEB4d8DHX0v9lZx2i9X23tp5%2BWMlSoxzWpjG4aY9MMoCiP5m%2BmXWzrTAxiGWpB7t7EyTUWtmktcBqilOlohT5Jy2DP2pxu9HJIE5JAzywOzdtKMpkuEvM1NmzS5qcUpUDWivoxZNajT0gz%2Fa1Dnr0dr2Ngku1YkYBfpCdBnmh09lKQmb4pWmJoIw9fv%2BjRmAwhFcf6OW5xoKwWiYu3r7tzY0UEsqAI%2BpPaVnp9bU4j0B%2BsZKPergPVqEPwSQ0k1oPgzmAH%2FMRHg6FjcBYci74ojPIWWnDrU5s%2FD222jb9hPeHyUBGvGhfgWGD84do7E8XY54WAeeadhGCzfvuGTwhxbefLRY33GSQttMb%2FZu9Oj3uxHM9FSwSqZBHaW90lLxC43jgHkA9mdkB9Rex%2B%2B16VXN2HJz2jRPXo1RKlU%2FgvonLZJP%2FacBj%2FmBmmi7ncUDsTcqy5lmtcLsCMIk4E8K355SBLNv0%2FnLCrGw7R3OQ6MB4KdNYfQ1019aYNcpSoJcNWP%2BG8eXDqlEg%2BknTSptOmC7bz6mrFDKkuPzoHrsjAUBtTzkQoObv3beYyCalPgzyz0cHa28nXBrzjvacsOLS6sAvkqWyU1xB%2B7%2BPrfuynfLMgdlMlg1ZmI4x70b%2BM6IxbZqm%2B9scHpiOXnS97%2Fm0hdEh4hURYgvTnbMNuvmZQGOpoBiaVOPRkpQ0AsJAc%2B1PGg7bZwfQKdFrZ6gxwOkbH57TroM6NHeXUSOeHeAFUfslUIzxgxuT78l8vAGtNmItS%2FgyMPyy21EiIO%2FleKBrKFPMtT70LiAUXEB2qO56nqTiVzXHKTzI0KlKU7PadSrG0dXDfW1ISSzTsc2eDVO1EOKP3Wa%2BVsXE6LCjfyh6Tc%2BxrgVvOuByhfdvJCgg%3D%3D&X-Amz-SignedHeaders=host&X-Amz-Signature=862aaf49ebb8118d1f572937a5fd7eabaacd9fbaca79282548cf54d99478a711",
        "cubemapGetUrl": "https://sapi-room-thumbnails.s3.amazonaws.com/6246b6964f7a930001a7636a/cubemap?X-Amz-Algorithm=AWS4-HMAC-SHA256&X-Amz-Credential=ASIAVFTG5JZHGIIZL7UX%2F20220519%2Fus-east-1%2Fs3%2Faws4_request&X-Amz-Date=20220519T153919Z&X-Amz-Expires=14400&X-Amz-Security-Token=IQoJb3JpZ2luX2VjEBcaCXVzLWVhc3QtMSJHMEUCIQDFmscNntmUCd%2F%2B6P%2BkXbIbbdZF%2F93sRzM%2Bh0UktEfPPwIgds6qF2w13DF0lUFa11Dd55JZJCyoS%2B2mUBdBwrY1EF0q9wQI8P%2F%2F%2F%2F%2F%2F%2F%2F%2F%2FARADGgwzNTU2MjQzNzM4MzgiDPqvgS0a%2BZGpTC44fSrLBKnkEz8MgaSxoR6XvzJ7EZyyuFJaSnmPFQT3kCsUrzj%2F%2Bz0mebUQVsXtkTu%2BTMW5uId90rm%2Fno2YIGATsTJdC5MnBZ1L%2BRRpLFr426peuygXGWEB4d8DHX0v9lZx2i9X23tp5%2BWMlSoxzWpjG4aY9MMoCiP5m%2BmXWzrTAxiGWpB7t7EyTUWtmktcBqilOlohT5Jy2DP2pxu9HJIE5JAzywOzdtKMpkuEvM1NmzS5qcUpUDWivoxZNajT0gz%2Fa1Dnr0dr2Ngku1YkYBfpCdBnmh09lKQmb4pWmJoIw9fv%2BjRmAwhFcf6OW5xoKwWiYu3r7tzY0UEsqAI%2BpPaVnp9bU4j0B%2BsZKPergPVqEPwSQ0k1oPgzmAH%2FMRHg6FjcBYci74ojPIWWnDrU5s%2FD222jb9hPeHyUBGvGhfgWGD84do7E8XY54WAeeadhGCzfvuGTwhxbefLRY33GSQttMb%2FZu9Oj3uxHM9FSwSqZBHaW90lLxC43jgHkA9mdkB9Rex%2B%2B16VXN2HJz2jRPXo1RKlU%2FgvonLZJP%2FacBj%2FmBmmi7ncUDsTcqy5lmtcLsCMIk4E8K355SBLNv0%2FnLCrGw7R3OQ6MB4KdNYfQ1019aYNcpSoJcNWP%2BG8eXDqlEg%2BknTSptOmC7bz6mrFDKkuPzoHrsjAUBtTzkQoObv3beYyCalPgzyz0cHa28nXBrzjvacsOLS6sAvkqWyU1xB%2B7%2BPrfuynfLMgdlMlg1ZmI4x70b%2BM6IxbZqm%2B9scHpiOXnS97%2Fm0hdEh4hURYgvTnbMNuvmZQGOpoBiaVOPRkpQ0AsJAc%2B1PGg7bZwfQKdFrZ6gxwOkbH57TroM6NHeXUSOeHeAFUfslUIzxgxuT78l8vAGtNmItS%2FgyMPyy21EiIO%2FleKBrKFPMtT70LiAUXEB2qO56nqTiVzXHKTzI0KlKU7PadSrG0dXDfW1ISSzTsc2eDVO1EOKP3Wa%2BVsXE6LCjfyh6Tc%2BxrgVvOuByhfdvJCgg%3D%3D&X-Amz-SignedHeaders=host&X-Amz-Signature=ac928fbaba0c6cdb1ce696086136d7d914c5125fcaeb83bbd3143e108f52de5b",
        "expiresAt": 1652989159000
      },
      "starred": true,
      "shareID": "4069560728893578203",
      "code": "",
      "shareSetting": "PRIVATE",
      "publicLink": true,
      "roomAdmins": [
        "61b21d6bc92b1b000110003c",
        "5f72ee5afa7f116d57153fee"
      ],
      "restrictedPermissions": [
        "RESTRICT_OTHERS_VIEW_ONLY"
      ],
      "directlyInvitedGuests": {},
      "lobbyType": "",
      "defaultRoomContent": null,
      "accessible": true,
      "createdAt": "2022-04-01T08:23:50.26Z",
      "tileSize": "large",
      "directlyInvitedGuestsArray": [],
      "active": true,
      "users": [
        "62849a10bf651d0001db1a01",
        "628663e1bf651d0001db5519"
      ],
      "likes": 0,
      "views": 0
    },
    {
      "id": "6246b7064f7a930001a76375",
      "ownerID": "6242c206d3dd2500016583cb",
      "owner": {
        "userID": "6242c206d3dd2500016583cb",
        "displayName": "Gobierno de Navarra"
      },
      "name": "AUDITORIO GOBIERNO DE NAVARRA",
      "slug": "AUDITORIO-GOBIERNO-DE-NAVARRA",
      "description": "",
      "orgOwner": {
        "id": "6242f0b97aeff10001025a0b",
        "name": "GobiernoNavarra",
        "subscription": {
          "subscriptionType": "",
          "subscriptionSource": "",
          "isActive": false
        }
      },
      "organizations": [
        "6242f0b97aeff10001025a0b"
      ],
      "timeLastJoined": "0001-01-01T00:00:00Z",
      "thumbnails": [],
      "activeParticipants": [
        {
          "id": "628639d4d7843c8ac8a92709",
          "displayName": "Aritz",
          "profilePicURL": "https://api.avatarsdk.com/avatars/0152dd54-3946-47ea-8bb6-ae25c6be1e2d/preview/",
          "avatarData": {
            "avatarUserID": "f769f742-6c23-4063-a717-bc7b3141c08f",
            "avatarID": "0152dd54-3946-47ea-8bb6-ae25c6be1e2d",
            "avatarBody": "https://dd2cgqlmnwvp5.cloudfront.net/avatar_generic_bodies/rpm_male_formal/model.glb",
            "filename": "",
            "skinColorOverride": "f3eddb",
            "shirtColorOverride": "ffffff",
            "readyPlayerMeThumbnails": {
              "upperBody": "https://renderapi.s3.amazonaws.com/ZoSZ8H3V0.png",
              "lowerBody": ""
            },
            "readyPlayerMeUrl": "https://d1a370nemizbjq.cloudfront.net/0516d7aa-39fc-4a32-8cd8-93982a3f4ed8.glb",
            "ReadyPlayerMeUrlLastUpdated": "0001-01-01T00:00:00Z",
            "readyPlayerMeUrlCrunched": "",
            "readyPlayerMeUrlCrunchedBrotli": "",
            "ReadyPlayerMeUrlCrunchedLastUpdated": "0001-01-01T00:00:00Z",
            "activeAvatarStyle": "REALISTIC"
          },
          "appearanceCustomization": {
            "profileColor": "green"
          },
          "clientPlatforms": [
            "WebGL",
            "WebGL",
            "WebGL",
            "WebGL"
          ],
          "permissions": [],
          "clientPlatform": "",
          "playerColor": "green"
        }
      ],
      "polymerVersion": 15,
      "roomThumbnails": {
        "transientGetUrl": "https://sapi-room-thumbnails.s3.amazonaws.com/6246b7064f7a930001a76375/transientStateThumbnail?X-Amz-Algorithm=AWS4-HMAC-SHA256&X-Amz-Credential=ASIAVFTG5JZHGIIZL7UX%2F20220519%2Fus-east-1%2Fs3%2Faws4_request&X-Amz-Date=20220519T153919Z&X-Amz-Expires=14400&X-Amz-Security-Token=IQoJb3JpZ2luX2VjEBcaCXVzLWVhc3QtMSJHMEUCIQDFmscNntmUCd%2F%2B6P%2BkXbIbbdZF%2F93sRzM%2Bh0UktEfPPwIgds6qF2w13DF0lUFa11Dd55JZJCyoS%2B2mUBdBwrY1EF0q9wQI8P%2F%2F%2F%2F%2F%2F%2F%2F%2F%2FARADGgwzNTU2MjQzNzM4MzgiDPqvgS0a%2BZGpTC44fSrLBKnkEz8MgaSxoR6XvzJ7EZyyuFJaSnmPFQT3kCsUrzj%2F%2Bz0mebUQVsXtkTu%2BTMW5uId90rm%2Fno2YIGATsTJdC5MnBZ1L%2BRRpLFr426peuygXGWEB4d8DHX0v9lZx2i9X23tp5%2BWMlSoxzWpjG4aY9MMoCiP5m%2BmXWzrTAxiGWpB7t7EyTUWtmktcBqilOlohT5Jy2DP2pxu9HJIE5JAzywOzdtKMpkuEvM1NmzS5qcUpUDWivoxZNajT0gz%2Fa1Dnr0dr2Ngku1YkYBfpCdBnmh09lKQmb4pWmJoIw9fv%2BjRmAwhFcf6OW5xoKwWiYu3r7tzY0UEsqAI%2BpPaVnp9bU4j0B%2BsZKPergPVqEPwSQ0k1oPgzmAH%2FMRHg6FjcBYci74ojPIWWnDrU5s%2FD222jb9hPeHyUBGvGhfgWGD84do7E8XY54WAeeadhGCzfvuGTwhxbefLRY33GSQttMb%2FZu9Oj3uxHM9FSwSqZBHaW90lLxC43jgHkA9mdkB9Rex%2B%2B16VXN2HJz2jRPXo1RKlU%2FgvonLZJP%2FacBj%2FmBmmi7ncUDsTcqy5lmtcLsCMIk4E8K355SBLNv0%2FnLCrGw7R3OQ6MB4KdNYfQ1019aYNcpSoJcNWP%2BG8eXDqlEg%2BknTSptOmC7bz6mrFDKkuPzoHrsjAUBtTzkQoObv3beYyCalPgzyz0cHa28nXBrzjvacsOLS6sAvkqWyU1xB%2B7%2BPrfuynfLMgdlMlg1ZmI4x70b%2BM6IxbZqm%2B9scHpiOXnS97%2Fm0hdEh4hURYgvTnbMNuvmZQGOpoBiaVOPRkpQ0AsJAc%2B1PGg7bZwfQKdFrZ6gxwOkbH57TroM6NHeXUSOeHeAFUfslUIzxgxuT78l8vAGtNmItS%2FgyMPyy21EiIO%2FleKBrKFPMtT70LiAUXEB2qO56nqTiVzXHKTzI0KlKU7PadSrG0dXDfW1ISSzTsc2eDVO1EOKP3Wa%2BVsXE6LCjfyh6Tc%2BxrgVvOuByhfdvJCgg%3D%3D&X-Amz-SignedHeaders=host&X-Amz-Signature=4d506f8eefb3aee0776c9f05b1429d3ae113f78314254c50cfe653efbc7f1cbb",
        "persistentGetUrl": "https://sapi-room-thumbnails.s3.amazonaws.com/6246b7064f7a930001a76375/persistentStateThumbnail?X-Amz-Algorithm=AWS4-HMAC-SHA256&X-Amz-Credential=ASIAVFTG5JZHGIIZL7UX%2F20220519%2Fus-east-1%2Fs3%2Faws4_request&X-Amz-Date=20220519T153919Z&X-Amz-Expires=14400&X-Amz-Security-Token=IQoJb3JpZ2luX2VjEBcaCXVzLWVhc3QtMSJHMEUCIQDFmscNntmUCd%2F%2B6P%2BkXbIbbdZF%2F93sRzM%2Bh0UktEfPPwIgds6qF2w13DF0lUFa11Dd55JZJCyoS%2B2mUBdBwrY1EF0q9wQI8P%2F%2F%2F%2F%2F%2F%2F%2F%2F%2FARADGgwzNTU2MjQzNzM4MzgiDPqvgS0a%2BZGpTC44fSrLBKnkEz8MgaSxoR6XvzJ7EZyyuFJaSnmPFQT3kCsUrzj%2F%2Bz0mebUQVsXtkTu%2BTMW5uId90rm%2Fno2YIGATsTJdC5MnBZ1L%2BRRpLFr426peuygXGWEB4d8DHX0v9lZx2i9X23tp5%2BWMlSoxzWpjG4aY9MMoCiP5m%2BmXWzrTAxiGWpB7t7EyTUWtmktcBqilOlohT5Jy2DP2pxu9HJIE5JAzywOzdtKMpkuEvM1NmzS5qcUpUDWivoxZNajT0gz%2Fa1Dnr0dr2Ngku1YkYBfpCdBnmh09lKQmb4pWmJoIw9fv%2BjRmAwhFcf6OW5xoKwWiYu3r7tzY0UEsqAI%2BpPaVnp9bU4j0B%2BsZKPergPVqEPwSQ0k1oPgzmAH%2FMRHg6FjcBYci74ojPIWWnDrU5s%2FD222jb9hPeHyUBGvGhfgWGD84do7E8XY54WAeeadhGCzfvuGTwhxbefLRY33GSQttMb%2FZu9Oj3uxHM9FSwSqZBHaW90lLxC43jgHkA9mdkB9Rex%2B%2B16VXN2HJz2jRPXo1RKlU%2FgvonLZJP%2FacBj%2FmBmmi7ncUDsTcqy5lmtcLsCMIk4E8K355SBLNv0%2FnLCrGw7R3OQ6MB4KdNYfQ1019aYNcpSoJcNWP%2BG8eXDqlEg%2BknTSptOmC7bz6mrFDKkuPzoHrsjAUBtTzkQoObv3beYyCalPgzyz0cHa28nXBrzjvacsOLS6sAvkqWyU1xB%2B7%2BPrfuynfLMgdlMlg1ZmI4x70b%2BM6IxbZqm%2B9scHpiOXnS97%2Fm0hdEh4hURYgvTnbMNuvmZQGOpoBiaVOPRkpQ0AsJAc%2B1PGg7bZwfQKdFrZ6gxwOkbH57TroM6NHeXUSOeHeAFUfslUIzxgxuT78l8vAGtNmItS%2FgyMPyy21EiIO%2FleKBrKFPMtT70LiAUXEB2qO56nqTiVzXHKTzI0KlKU7PadSrG0dXDfW1ISSzTsc2eDVO1EOKP3Wa%2BVsXE6LCjfyh6Tc%2BxrgVvOuByhfdvJCgg%3D%3D&X-Amz-SignedHeaders=host&X-Amz-Signature=f8317daa6a8feb8eb40ffb4a7b81dfb14b91626f64b6c711e1b6348038f95e5f",
        "cubemapGetUrl": "https://sapi-room-thumbnails.s3.amazonaws.com/6246b7064f7a930001a76375/cubemap?X-Amz-Algorithm=AWS4-HMAC-SHA256&X-Amz-Credential=ASIAVFTG5JZHGIIZL7UX%2F20220519%2Fus-east-1%2Fs3%2Faws4_request&X-Amz-Date=20220519T153919Z&X-Amz-Expires=14400&X-Amz-Security-Token=IQoJb3JpZ2luX2VjEBcaCXVzLWVhc3QtMSJHMEUCIQDFmscNntmUCd%2F%2B6P%2BkXbIbbdZF%2F93sRzM%2Bh0UktEfPPwIgds6qF2w13DF0lUFa11Dd55JZJCyoS%2B2mUBdBwrY1EF0q9wQI8P%2F%2F%2F%2F%2F%2F%2F%2F%2F%2FARADGgwzNTU2MjQzNzM4MzgiDPqvgS0a%2BZGpTC44fSrLBKnkEz8MgaSxoR6XvzJ7EZyyuFJaSnmPFQT3kCsUrzj%2F%2Bz0mebUQVsXtkTu%2BTMW5uId90rm%2Fno2YIGATsTJdC5MnBZ1L%2BRRpLFr426peuygXGWEB4d8DHX0v9lZx2i9X23tp5%2BWMlSoxzWpjG4aY9MMoCiP5m%2BmXWzrTAxiGWpB7t7EyTUWtmktcBqilOlohT5Jy2DP2pxu9HJIE5JAzywOzdtKMpkuEvM1NmzS5qcUpUDWivoxZNajT0gz%2Fa1Dnr0dr2Ngku1YkYBfpCdBnmh09lKQmb4pWmJoIw9fv%2BjRmAwhFcf6OW5xoKwWiYu3r7tzY0UEsqAI%2BpPaVnp9bU4j0B%2BsZKPergPVqEPwSQ0k1oPgzmAH%2FMRHg6FjcBYci74ojPIWWnDrU5s%2FD222jb9hPeHyUBGvGhfgWGD84do7E8XY54WAeeadhGCzfvuGTwhxbefLRY33GSQttMb%2FZu9Oj3uxHM9FSwSqZBHaW90lLxC43jgHkA9mdkB9Rex%2B%2B16VXN2HJz2jRPXo1RKlU%2FgvonLZJP%2FacBj%2FmBmmi7ncUDsTcqy5lmtcLsCMIk4E8K355SBLNv0%2FnLCrGw7R3OQ6MB4KdNYfQ1019aYNcpSoJcNWP%2BG8eXDqlEg%2BknTSptOmC7bz6mrFDKkuPzoHrsjAUBtTzkQoObv3beYyCalPgzyz0cHa28nXBrzjvacsOLS6sAvkqWyU1xB%2B7%2BPrfuynfLMgdlMlg1ZmI4x70b%2BM6IxbZqm%2B9scHpiOXnS97%2Fm0hdEh4hURYgvTnbMNuvmZQGOpoBiaVOPRkpQ0AsJAc%2B1PGg7bZwfQKdFrZ6gxwOkbH57TroM6NHeXUSOeHeAFUfslUIzxgxuT78l8vAGtNmItS%2FgyMPyy21EiIO%2FleKBrKFPMtT70LiAUXEB2qO56nqTiVzXHKTzI0KlKU7PadSrG0dXDfW1ISSzTsc2eDVO1EOKP3Wa%2BVsXE6LCjfyh6Tc%2BxrgVvOuByhfdvJCgg%3D%3D&X-Amz-SignedHeaders=host&X-Amz-Signature=fda9b04003b15257432395ab53f1878a68e375b571d11a96f26902c7e8447dce",
        "expiresAt": 1652989159000
      },
      "starred": true,
      "shareID": "5152266806103099508",
      "code": "",
      "shareSetting": "PRIVATE",
      "publicLink": true,
      "roomAdmins": [
        "61b21d6bc92b1b000110003c",
        "61af925bc9bee600014349af"
      ],
      "restrictedPermissions": [
        "RESTRICT_OTHERS_VIEW_ONLY"
      ],
      "directlyInvitedGuests": {},
      "lobbyType": "",
      "defaultRoomContent": null,
      "accessible": true,
      "createdAt": "2022-04-01T08:25:42.041Z",
      "directlyInvitedGuestsArray": [],
      "active": true,
      "users": [
        "628639d4d7843c8ac8a92709"
      ],
      "likes": 0,
      "views": 0
    }
  ],
  "paging": {
    "total": 2
  }
}
